caldera/__init__.py
caldera/_setup/__init__.py
caldera/_setup/setup_nx_global_access.py
caldera/_version.py
caldera/blocks/__init__.py
caldera/blocks/aggregator.py
caldera/blocks/block.py
caldera/blocks/edge_block.py
caldera/blocks/flex.py
caldera/blocks/global_block.py
caldera/blocks/mlp.py
caldera/blocks/node_block.py
caldera/blocks/select.py
caldera/data/__init__.py
caldera/data/_graph_batch.py
caldera/data/_graph_data.py
caldera/data/_graph_tuple.py
caldera/data/_loader.py
caldera/data/utils/__init__.py
caldera/data/utils/_add_edges.py
caldera/data/utils/_floyd_warshall.py
caldera/data/utils/_matrix.py
caldera/data/utils/_sparse.py
caldera/data/utils/_traversal.py
caldera/data/utils/_utils.py
caldera/dataset/__init__.py
caldera/dataset/_graph_dataset.py
caldera/defaults.py
caldera/exceptions.py
caldera/models/__init__.py
caldera/models/base.py
caldera/models/encoder_core_decoder.py
caldera/models/graph_core.py
caldera/models/graph_encoder.py
caldera/testing/__init__.py
caldera/transforms/__init__.py
caldera/transforms/_add_self_loops.py
caldera/transforms/_base.py
caldera/transforms/_compose.py
caldera/transforms/_fully_connected.py
caldera/transforms/_random_edge_mask.py
caldera/transforms/_random_hop.py
caldera/transforms/_random_node_mask.py
caldera/transforms/_reverse.py
caldera/transforms/_shuffle.py
caldera/transforms/_undirected.py
caldera/transforms/networkx/__init__.py
caldera/transforms/networkx/_base.py
caldera/transforms/networkx/_nx_apply_to_graph.py
caldera/transforms/networkx/_nx_apply_to_key.py
caldera/transforms/networkx/_nx_attach_np_features.py
caldera/transforms/networkx/_nx_deepcopy.py
caldera/transforms/networkx/_nx_defaults.py
caldera/transforms/networkx/_nx_feature_transform.py
caldera/transforms/networkx/_nx_filter_keys.py
caldera/transforms/networkx/_nx_flatten_feature.py
caldera/transforms/networkx/_nx_freeze.py
caldera/transforms/networkx/_nx_nodes_to_str.py
caldera/transforms/networkx/_nx_to_directed.py
pytorch_caldera-0.0.1.dist-info/LICENSE
pytorch_caldera-0.0.1.dist-info/WHEEL
pytorch_caldera-0.0.1.dist-info/METADATA
pytorch_caldera-0.0.1.dist-info/RECORD
