Metadata-Version: 2.1
Name: pytorch-caldera
Version: 0.0.1
Summary: 
Home-page: http://www.github.com/jvrana/caldera
Keywords: pytorch,machine learning,network,graph
Author: Justin Vrana
Author-email: justin.vrana@gmail.com
Requires-Python: >=3.7,<4.0
Classifier: Intended Audience :: Developers
Classifier: Intended Audience :: Education
Classifier: Intended Audience :: Science/Research
Classifier: Programming Language :: Python :: 3
Classifier: Programming Language :: Python :: 3.7
Classifier: Programming Language :: Python :: 3.8
Classifier: Topic :: Scientific/Engineering
Classifier: Topic :: Scientific/Engineering :: Artificial Intelligence
Classifier: Topic :: Scientific/Engineering :: Mathematics
Classifier: Topic :: Software Development
Classifier: Topic :: Software Development :: Libraries
Classifier: Topic :: Software Development :: Libraries :: Python Modules
Provides-Extra: docs
Provides-Extra: lint
Provides-Extra: nbexamples
Provides-Extra: xtests
Requires-Dist: attrs (>=20.2.0,<21.0.0)
Requires-Dist: black (>=19.10b0,<20.0); extra == "lint"
Requires-Dist: colorama (>=0.4.3,<0.5.0)
Requires-Dist: dill (>=0.3.2,<0.4.0)
Requires-Dist: h5py (>=2.10.0,<3.0.0); extra == "nbexamples"
Requires-Dist: hydra-core (>=1.0.0,<2.0.0); extra == "nbexamples"
Requires-Dist: jupyter-sphinx (>=0.3.1,<0.4.0); extra == "docs"
Requires-Dist: keats (>=0.2.28,<0.3.0); extra == "docs"
Requires-Dist: matplotlib (>=3.3.1,<4.0.0); extra == "nbexamples"
Requires-Dist: nbconvert (>=5.6.1,<6.0.0); extra == "docs"
Requires-Dist: nbformat (>=5.0.7,<6.0.0); extra == "docs"
Requires-Dist: networkx (>=2.4,<3.0)
Requires-Dist: numpy (>=1.18.4,<2.0.0)
Requires-Dist: pre-commit (>=2.6.0,<3.0.0); extra == "lint"
Requires-Dist: pylint (>=2.5.3,<3.0.0); extra == "lint"
Requires-Dist: pytest-cov (>=2.10.0,<3.0.0); extra == "lint"
Requires-Dist: pytest-randomly (>=3.4.1,<4.0.0)
Requires-Dist: pytest-sugar (>=0.9.4,<0.10.0); extra == "xtests"
Requires-Dist: pytorch-lightning (>=0.9.0,<0.10.0); extra == "nbexamples"
Requires-Dist: rich (>=7.0.0,<8.0.0); extra == "nbexamples"
Requires-Dist: scipy (>=1.5.2,<2.0.0)
Requires-Dist: seaborn (>=0.11.0,<0.12.0); extra == "nbexamples"
Requires-Dist: sphinx (>=3.2.1,<4.0.0); extra == "docs"
Requires-Dist: sphinx_autodoc_typehints (>=1.11.0,<2.0.0); extra == "docs"
Requires-Dist: sphinx_bootstrap_theme (>=0.7.1,<0.8.0); extra == "docs"
Requires-Dist: torch (>=1.5.0,<2.0.0)
Requires-Dist: torch-scatter (>=2.0.4,<3.0.0)
Requires-Dist: tqdm (>=4.48.2,<5.0.0); extra == "nbexamples"
